Metadata-Version: 1.1
Name: infinite-scroll-boolean
Version: 0.0.1
Summary: Boolean waypoint component for infinite scrolling in dash
Home-page: UNKNOWN
Author: Khalim Conn-Kowlessar <khalim@exii.co>
Author-email: UNKNOWN
License: MIT
Platform: UNKNOWN
Classifier: Framework :: Dash
